hokusai/RELEASE_VERSION
hokusai/VERSION
hokusai/__init__.py
hokusai/cli/__init__.py
hokusai/cli/base.py
hokusai/cli/dev.py
hokusai/cli/pipeline.py
hokusai/cli/production.py
hokusai/cli/registry.py
hokusai/cli/review_app.py
hokusai/cli/staging.py
hokusai/command_line.py
hokusai/commands/__init__.py
hokusai/commands/build.py
hokusai/commands/check.py
hokusai/commands/command_tree.py
hokusai/commands/configure.py
hokusai/commands/deployment.py
hokusai/commands/development.py
hokusai/commands/env.py
hokusai/commands/gitcompare.py
hokusai/commands/gitdiff.py
hokusai/commands/gitlog.py
hokusai/commands/images.py
hokusai/commands/kubernetes.py
hokusai/commands/logs.py
hokusai/commands/pull.py
hokusai/commands/push.py
hokusai/commands/retag.py
hokusai/commands/review_app.py
hokusai/commands/run.py
hokusai/commands/setup.py
hokusai/commands/test.py
hokusai/commands/version.py
hokusai/lib/__init__.py
hokusai/lib/command.py
hokusai/lib/common.py
hokusai/lib/config.py
hokusai/lib/config_loader.py
hokusai/lib/constants.py
hokusai/lib/docker_compose_helpers.py
hokusai/lib/environment.py
hokusai/lib/exceptions.py
hokusai/lib/global_config.py
hokusai/lib/representers.py
hokusai/lib/template_renderer.py
hokusai/lib/template_selector.py
hokusai/services/__init__.py
hokusai/services/command_runner.py
hokusai/services/configmap.py
hokusai/services/deployment.py
hokusai/services/docker.py
hokusai/services/ecr.py
hokusai/services/kubectl.py
hokusai/services/namespace.py
hokusai/services/s3.py
hokusai/services/service_account.py
hokusai/services/yaml_spec.py
hokusai/templates/.dockerignore.j2
hokusai/templates/Dockerfile.j2
hokusai/templates/hokusai/build.yml.j2
hokusai/templates/hokusai/development.yml.j2
hokusai/templates/hokusai/production.yml.j2
hokusai/templates/hokusai/staging.yml.j2
hokusai/templates/hokusai/test.yml.j2
hokusai/version.py
hokusai-3.2.0.dist-info/entry_points.txt
hokusai-3.2.0.dist-info/LICENSE.txt
hokusai-3.2.0.dist-info/WHEEL
hokusai-3.2.0.dist-info/METADATA
hokusai-3.2.0.dist-info/RECORD
