Metadata-Version: 2.1
Name: hokusai
Version: 3.2.0
Summary: Artsy Docker development toolkit
Home-page: http://github.com/artsy/hokusai
License: MIT
Author: Isac Petruzzi
Author-email: isac@artsymail.com
Maintainer: Jian-Feng Xu
Maintainer-email: jian-feng@artsymail.com
Requires-Python: >=3.9,<3.11
Classifier: License :: OSI Approved :: MIT License
Classifier: Programming Language :: Python :: 3
Classifier: Programming Language :: Python :: 3.9
Classifier: Programming Language :: Python :: 3.10
Requires-Dist: Jinja2 (==3.1.1)
Requires-Dist: MarkupSafe (==2.1.1)
Requires-Dist: PyYAML (==6.0.1)
Requires-Dist: boto3 (>=1.34.25,<2.0.0)
Requires-Dist: click (==8.1.0)
Requires-Dist: click-repl (==0.2.0)
Requires-Dist: packaging (>=24.1,<25.0)
Requires-Dist: prompt-toolkit (==3.0.28)
Requires-Dist: termcolor (==1.1.0)
Project-URL: Repository, http://github.com/artsy/hokusai
